adafruit_circuitpython_cursorcontrol-2.9.5.dist-info/licenses/LICENSE
adafruit_cursorcontrol/__init__.py
adafruit_cursorcontrol/cursorcontrol.py
adafruit_cursorcontrol/cursorcontrol_cursormanager.py
adafruit_circuitpython_cursorcontrol-2.9.5.dist-info/METADATA
adafruit_circuitpython_cursorcontrol-2.9.5.dist-info/WHEEL
adafruit_circuitpython_cursorcontrol-2.9.5.dist-info/top_level.txt
adafruit_circuitpython_cursorcontrol-2.9.5.dist-info/RECORD
