Metadata-Version: 2.4
Name: adafruit-circuitpython-cursorcontrol
Version: 2.9.5
Summary: Mouse cursor for interaction with CircuitPython UI elements.
Author-email: Adafruit Industries <circuitpython@adafruit.com>
License: MIT
Project-URL: Homepage, https://github.com/adafruit/Adafruit_CircuitPython_CursorControl
Keywords: adafruit,blinka,circuitpython,micropython,cursorcontrol,mouse,,cursor,,ui
Classifier: Intended Audience :: Developers
Classifier: Topic :: Software Development :: Libraries
Classifier: Topic :: Software Development :: Embedded Systems
Classifier: Topic :: System :: Hardware
Classifier: License :: OSI Approved :: MIT License
Classifier: Programming Language :: Python :: 3
License-File: LICENSE
Requires-Dist: Adafruit-Blinka
Requires-Dist: Adafruit-Blinka-Displayio
Requires-Dist: adafruit-circuitpython-debouncer
Requires-Dist: adafruit-circuitpython-typing
Provides-Extra: optional
Dynamic: license-file
